README
setup.py
anyjson/__init__.py
anyjson.egg-info/PKG-INFO
anyjson.egg-info/SOURCES.txt
anyjson.egg-info/dependency_links.txt
anyjson.egg-info/not-zip-safe
anyjson.egg-info/top_level.txt