Metadata-Version: 1.0
Name: anyjson
Version: 0.2.2
Summary: Wraps the best available JSON implementation available in a common
Home-page: http://bitbucket.org/runeh/anyjson
Author: Rune Halvorsen
Author-email: runefh@gmail.com
License: BSD
Keywords: json
Platform: any
Classifier: License :: OSI Approved :: BSD License
Classifier: Intended Audience :: Developers
Classifier: Programming Language :: Python
